odoo/addons/account_statement_import_paypal/README.rst
odoo/addons/account_statement_import_paypal/__init__.py
odoo/addons/account_statement_import_paypal/__manifest__.py
odoo/addons/account_statement_import_paypal/data/maps.xml
odoo/addons/account_statement_import_paypal/i18n/account_statement_import_paypal.pot
odoo/addons/account_statement_import_paypal/i18n/es.po
odoo/addons/account_statement_import_paypal/i18n/es_AR.po
odoo/addons/account_statement_import_paypal/i18n/it.po
odoo/addons/account_statement_import_paypal/models/__init__.py
odoo/addons/account_statement_import_paypal/models/account_journal.py
odoo/addons/account_statement_import_paypal/models/account_statement_import.py
odoo/addons/account_statement_import_paypal/models/account_statement_import_paypal_mapping.py
odoo/addons/account_statement_import_paypal/models/account_statement_import_paypal_parser.py
odoo/addons/account_statement_import_paypal/readme/CONFIGURE.md
odoo/addons/account_statement_import_paypal/readme/CONTRIBUTORS.md
odoo/addons/account_statement_import_paypal/readme/DESCRIPTION.md
odoo/addons/account_statement_import_paypal/readme/HISTORY.md
odoo/addons/account_statement_import_paypal/readme/USAGE.md
odoo/addons/account_statement_import_paypal/security/ir.model.access.csv
odoo/addons/account_statement_import_paypal/static/description/icon.png
odoo/addons/account_statement_import_paypal/static/description/index.html
odoo/addons/account_statement_import_paypal/tests/__init__.py
odoo/addons/account_statement_import_paypal/tests/test_account_statement_import_paypal.py
odoo/addons/account_statement_import_paypal/tests/fixtures/activity_en.csv
odoo/addons/account_statement_import_paypal/tests/fixtures/empty_activity.csv
odoo/addons/account_statement_import_paypal/tests/fixtures/statement_en.csv
odoo/addons/account_statement_import_paypal/tests/fixtures/statement_es.csv
odoo/addons/account_statement_import_paypal/views/account_statement_import.xml
odoo_addon_account_statement_import_paypal-17.0.1.0.0.4.dist-info/METADATA
odoo_addon_account_statement_import_paypal-17.0.1.0.0.4.dist-info/WHEEL
odoo_addon_account_statement_import_paypal-17.0.1.0.0.4.dist-info/top_level.txt
odoo_addon_account_statement_import_paypal-17.0.1.0.0.4.dist-info/RECORD
