Metadata-Version: 2.1
Name: odoo-addon-account_statement_import_paypal
Version: 17.0.1.0.0.4
Requires-Python: >=3.10
Requires-Dist: odoo-addon-account_statement_import_file>=17.0dev,<17.1dev
Requires-Dist: odoo-addon-multi_step_wizard>=17.0dev,<17.1dev
Requires-Dist: odoo-addon-web_widget_dropdown_dynamic>=17.0dev,<17.1dev
Requires-Dist: odoo>=17.0a,<17.1dev
Summary: Import PayPal CSV files as Bank Statements in Odoo
Home-page: https://github.com/OCA/bank-statement-import
License: AGPL-3
Author: Akretion, CorporateHub, Odoo Community Association (OCA)
Author-email: support@odoo-community.org
Classifier: Programming Language :: Python
Classifier: Framework :: Odoo
Classifier: Framework :: Odoo :: 17.0
Classifier: License :: OSI Approved :: GNU Affero General Public License v3
